{
  "version": 1,
  "task_id": "T001",
  "title": "Record implementation guardrail and embedded review baseline in .specify/features/2026-07-08-launchdeck-global-cli-control-plane/implementation-review/ledger.json",
  "phase": "Phase 0",
  "story": null,
  "priority": null,
  "agent": "quality-reviewer",
  "depends_on": [],
  "parallel_safe": false,
  "target_root": "F:/github/launchdeck",
  "evidence_status": "project cognition partial_refresh/review; live reads and plan artifacts required",
  "context_navigation": [
    {
      "need": "Locked decisions",
      "ref": "plan.md#locked-planning-decisions"
    },
    {
      "need": "Implementation constitution",
      "ref": "plan.md#implementation-constitution"
    },
    {
      "need": "State model",
      "ref": "data-model.md#storage-namespaces"
    },
    {
      "need": "CLI contract",
      "ref": "contracts/cli-contract.md#cli-contract-launchdeck-global-cli-control-plane"
    },
    {
      "need": "Validation scenario",
      "ref": "quickstart.md#quickstart-launchdeck-global-cli-control-plane"
    },
    {
      "need": "Review policy",
      "ref": "plan.md#review-focus"
    }
  ],
  "scope_boundaries": {
    "write_scope": [
      ".specify/features/2026-07-08-launchdeck-global-cli-control-plane/implementation-review/ledger.json"
    ],
    "read_scope": [
      "F:/github/launchdeck/.specify/features/2026-07-08-launchdeck-global-cli-control-plane/spec.md",
      "F:/github/launchdeck/.specify/features/2026-07-08-launchdeck-global-cli-control-plane/plan.md",
      "F:/github/launchdeck/.specify/features/2026-07-08-launchdeck-global-cli-control-plane/data-model.md",
      "F:/github/launchdeck/.specify/features/2026-07-08-launchdeck-global-cli-control-plane/contracts/cli-contract.md",
      "F:/github/launchdeck/.specify/features/2026-07-08-launchdeck-global-cli-control-plane/quickstart.md",
      "F:/github/launchdeck/.specify/features/2026-07-08-launchdeck-global-cli-control-plane/plan-contract.json",
      "F:/github/launchdeck/.specify/memory/constitution.md"
    ],
    "forbidden": [
      ".env",
      ".env.*",
      "**/*secret*",
      "**/*credential*",
      "**/node_modules/**",
      "F:/github/* outside F:/github/launchdeck"
    ]
  },
  "expected_outputs": [
    "implementation-review/ledger.json (new)"
  ],
  "anti_goals": [
    "Do not edit Launchdeck source or tests in this guardrail task."
  ],
  "does_not_remove": [
    "Specification-first flow",
    "embedded implement review"
  ],
  "capability_operations": [
    "preserves all CLI lifecycle operations without implementing them"
  ],
  "consumer_surfaces": [],
  "required_evidence": [],
  "acceptance_criteria": [
    "Ledger records Standard Delivery profile, Senior Consequence Gate, no daemon, no external kill, owned-only stop, JSON contract, and review window policy."
  ],
  "verify_commands": [
    "Test-Path .specify/features/2026-07-08-launchdeck-global-cli-control-plane/implementation-review/ledger.json"
  ],
  "guardrails": [
    "G-BOUNDARY",
    "G-NO-DAEMON"
  ],
  "mp": [
    "MP-001",
    "MP-003",
    "MP-005",
    "MP-007",
    "MP-011",
    "MP-013"
  ],
  "ca": [
    "CA-CP-017"
  ],
  "fr": [
    "FR-019",
    "FR-020",
    "FR-021"
  ],
  "boundary_constraints": [
    "CLI-only",
    "daemonless first",
    "user-scoped state",
    "no external kill",
    "owned-only stop/restart",
    "safe clean only",
    "stable JSON envelope"
  ],
  "stop_and_reopen": [
    "External kill becomes required in base scope.",
    "Daemon or service implementation becomes mandatory for this feature.",
    "GUI, TUI, MCP, or editor implementation becomes mandatory for this feature.",
    "Clean absorbs destructive reset semantics.",
    "Default scope changes from user-scoped to whole-machine or multi-user.",
    "Safety invariants conflict with feasible cross-platform implementation."
  ],
  "handoff_format": {
    "status": "success | failed | blocked",
    "changed_files": [
      ".specify/features/2026-07-08-launchdeck-global-cli-control-plane/implementation-review/ledger.json"
    ],
    "validation_output": {
      "Test-Path .specify/features/2026-07-08-launchdeck-global-cli-control-plane/implementation-review/ledger.json": "<paste relevant output>"
    },
    "concerns": [],
    "recovery_hints": []
  },
  "retry_max": 2,
  "escalation": "debugger",
  "independent_executability_gate": "ready: worker can complete using this packet and referenced context files"
}